nlp12/__init__.py
nlp12-1.12.0.dist-info/METADATA
nlp12-1.12.0.dist-info/WHEEL
nlp12-1.12.0.dist-info/top_level.txt
nlp12-1.12.0.dist-info/RECORD
